README.rst
setup.py
pyrthon/__init__.py
pyrthon/_console.py
pyrthon/_import_hook.py
pyrthon/_transformer.py
pyrthon/_version.py
pyrthon/console.py
pyrthon/pyrthon_extension.py
pyrthon.egg-info/PKG-INFO
pyrthon.egg-info/SOURCES.txt
pyrthon.egg-info/dependency_links.txt
pyrthon.egg-info/requires.txt
pyrthon.egg-info/top_level.txt