Metadata-Version: 1.1
Name: pyrthon
Version: 0.1.2
Summary: Literal syntax for Pyrsistent data structures
Home-page: http://github.com/tobgu/pyrthon/
Author: Tobias Gustafsson
Author-email: tobias.l.gustafsson@gmail.com
License: MIT
Platform: UNKNOWN
Classifier: Intended Audience :: Developers
Classifier: License :: OSI Approved :: MIT License
Classifier: Operating System :: OS Independent
Classifier: Programming Language :: Python
